mima/__init__.py
mima/py.typed
mima/advanced/__init__.py
mima/advanced/assets.py
mima/advanced/scene.py
mima/advanced/shape.py
mima/advanced/shaped_sprite.py
mima/backend/__init__.py
mima/backend/pygame_assets.py
mima/backend/pygame_audio.py
mima/backend/pygame_backend.py
mima/backend/pygame_camera.py
mima/backend/pygame_events.py
mima/backend/touch_control_scheme_a.py
mima/backend/touch_control_scheme_b.py
mima/core/__init__.py
mima/core/collision.py
mima/core/database.py
mima/core/engine.py
mima/core/mode_engine.py
mima/core/scene_engine.py
mima/maps/__init__.py
mima/maps/template.py
mima/maps/tile.py
mima/maps/tile_animation.py
mima/maps/tile_info.py
mima/maps/tile_layer.py
mima/maps/tilemap.py
mima/maps/tileset.py
mima/maps/tileset_info.py
mima/maps/transition_map.py
mima/maps/tiled/__init__.py
mima/maps/tiled/tiled_layer.py
mima/maps/tiled/tiled_map.py
mima/maps/tiled/tiled_object.py
mima/maps/tiled/tiled_objectgroup.py
mima/maps/tiled/tiled_template.py
mima/maps/tiled/tiled_tile.py
mima/maps/tiled/tiled_tileset.py
mima/objects/__init__.py
mima/objects/animated_sprite.py
mima/objects/attribute_effect.py
mima/objects/attributes.py
mima/objects/creature.py
mima/objects/dynamic.py
mima/objects/loader.py
mima/objects/projectile.py
mima/objects/sprite.py
mima/objects/effects/__init__.py
mima/objects/effects/colorize_screen.py
mima/objects/effects/debug_box.py
mima/objects/effects/light.py
mima/objects/effects/show_sprite.py
mima/objects/effects/walking_on_grass.py
mima/objects/effects/walking_on_water.py
mima/objects/world/__init__.py
mima/objects/world/color_gate.py
mima/objects/world/color_switch.py
mima/objects/world/container.py
mima/objects/world/floor_switch.py
mima/objects/world/gate.py
mima/objects/world/light_source.py
mima/objects/world/logic_gate.py
mima/objects/world/movable.py
mima/objects/world/oneway.py
mima/objects/world/pickup.py
mima/objects/world/switch.py
mima/objects/world/teleport.py
mima/scripts/__init__.py
mima/scripts/command.py
mima_engine-0.3.3.dist-info/METADATA
mima_engine-0.3.3.dist-info/WHEEL
mima_engine-0.3.3.dist-info/RECORD
