Metadata-Version: 2.4
Name: mima-engine
Version: 0.3.3
Summary: A game engine based on pygame.
Author-email: Stephan Balduin <stephan.balduin@mailbox.org>
Classifier: License :: OSI Approved :: MIT License
Classifier: Programming Language :: Python :: 3
Requires-Python: >=3.12
Provides-Extra: ce
Requires-Dist: pygame-ce; extra == 'ce'
Provides-Extra: dev
Requires-Dist: build; extra == 'dev'
Requires-Dist: pygame-ce; extra == 'dev'
Requires-Dist: pytest; extra == 'dev'
Requires-Dist: twine; extra == 'dev'
Provides-Extra: pygame
Requires-Dist: pygame; extra == 'pygame'
